suite_validation/__init__.py
suite_validation/_gcov_coverage.py
suite_validation/_logger.py
suite_validation/_tool_info.py
suite_validation/coverage.py
suite_validation/execution.py
suite_validation/execution_utils.py
suite_validation/harness.c
suite_validation/label-adder
suite_validation/metadata_utils.py
suite_validation/plotting.py
suite_validation/reduction_strategy.py
suite_validation/test_coverage.py
suite_validation/test_execution.py
suite_validation/transformer.py
suite_validation/writer.py
TestCov-3.7.dist-info/Apache-2.0.txt
TestCov-3.7.dist-info/METADATA
TestCov-3.7.dist-info/WHEEL
TestCov-3.7.dist-info/entry_points.txt
TestCov-3.7.dist-info/top_level.txt
TestCov-3.7.dist-info/zip-safe
TestCov-3.7.dist-info/RECORD
