Metadata-Version: 2.1
Name: TestCov
Version: 3.7
Summary: A container-based test-suite executor with coverage measurement
Home-page: https://gitlab.com/sosy-lab/software/test-suite-validator
Author: Dirk Beyer
Author-email: dirk.beyer@sosy-lab.org
License: Apache-2.0
Project-URL: Changelog, https://gitlab.com/sosy-lab/software/test-suite-validator/-/blob/main/CHANGELOG.md
Project-URL: Issue Tracker, https://gitlab.com/sosy-lab/software/test-suite-validator/-/issues
Keywords: C,testing,test suite,test-case generation,verification
Platform: UNKNOWN
Classifier: Development Status :: 5 - Production/Stable
Classifier: Environment :: Console
Classifier: Intended Audience :: Science/Research
Classifier: License :: OSI Approved :: Apache Software License
Classifier: Operating System :: POSIX :: Linux
Classifier: Programming Language :: Python :: 3 :: Only
Classifier: Topic :: Software Development :: Testing
Requires-Python: >=3.6
License-File: LICENSES/Apache-2.0.txt
Requires-Dist: lxml (>=4.0.0)
Requires-Dist: benchexec (>=1.20)
Requires-Dist: pycparser (>=2.19)
Requires-Dist: numpy (>=1.15)
Requires-Dist: tsbuilder (>=2.0)
